rbxstats/__init__.py
rbxstats/client.py
rbxstats/exceptions.py
rbxstats/models.py
rbxstats/utils.py
rbxstats-3.1.0.dist-info/licenses/LICENSE
rbxstats-3.1.0.dist-info/METADATA
rbxstats-3.1.0.dist-info/WHEEL
rbxstats-3.1.0.dist-info/top_level.txt
rbxstats-3.1.0.dist-info/RECORD
