Metadata-Version: 2.4
Name: rbxstats
Version: 3.1.0
Summary: A comprehensive Python client for the RbxStats API
Home-page: https://github.com/Rbxstats/Rbxstats_Pypi
Author: RbxStats Team
Author-email: rbxstatsxyz@gmail.com
License: MIT
Project-URL: Documentation, https://github.com/Rbxstats/Rbxstats_Pypi#readme
Project-URL: Source, https://github.com/Rbxstats/Rbxstats_Pypi
Project-URL: Tracker, https://github.com/Rbxstats/Rbxstats_Pypi/issues
Keywords: roblox api client rbxstats
Classifier: Development Status :: 4 - Beta
Classifier: Intended Audience :: Developers
Classifier: License :: OSI Approved :: MIT License
Classifier: Programming Language :: Python :: 3
Classifier: Programming Language :: Python :: 3.7
Classifier: Programming Language :: Python :: 3.8
Classifier: Programming Language :: Python :: 3.9
Classifier: Programming Language :: Python :: 3.10
Classifier: Operating System :: OS Independent
Requires-Python: >=3.7
License-File: LICENSE
Requires-Dist: requests>=2.25.0
Requires-Dist: aiohttp>=3.7.0
Dynamic: author
Dynamic: author-email
Dynamic: classifier
Dynamic: description
Dynamic: description-content-type
Dynamic: home-page
Dynamic: keywords
Dynamic: license
Dynamic: license-file
Dynamic: project-url
Dynamic: requires-dist
Dynamic: requires-python
Dynamic: summary
